satviz/__init__.py
satviz/static/widget.css
satviz/static/widget.js
satviz-0.4.0.dist-info/METADATA
satviz-0.4.0.dist-info/WHEEL
satviz-0.4.0.dist-info/RECORD
