Metadata-Version: 2.4
Name: satviz
Version: 0.4.0
Summary: SatSimJS widget for Jupyter and Marimo (Cesium-based)
Project-URL: Homepage, https://github.com/ssc-ai/satviz
Project-URL: Repository, https://github.com/ssc-ai/satviz
Project-URL: Issues, https://github.com/ssc-ai/satviz/issues
Author: Alex Cabello
Keywords: anywidget,cesium,jupyter,marimo,satellite,visualization
Classifier: Development Status :: 3 - Alpha
Classifier: Framework :: Jupyter
Classifier: Intended Audience :: Developers
Classifier: Intended Audience :: Science/Research
Classifier: Programming Language :: Python
Classifier: Programming Language :: Python :: 3
Classifier: Programming Language :: Python :: 3 :: Only
Classifier: Topic :: Scientific/Engineering :: Visualization
Classifier: Typing :: Typed
Requires-Python: >=3.9
Requires-Dist: anywidget
Provides-Extra: dev
Requires-Dist: jupyterlab; extra == 'dev'
Requires-Dist: marimo>=0.14.16; extra == 'dev'
Requires-Dist: watchfiles; extra == 'dev'
